eircode_pkg/__init__.py
eircode_pkg/eircode_validator.py
eircode_validator_24203203-0.1.3.dist-info/LICENSE
eircode_validator_24203203-0.1.3.dist-info/METADATA
eircode_validator_24203203-0.1.3.dist-info/WHEEL
eircode_validator_24203203-0.1.3.dist-info/top_level.txt
eircode_validator_24203203-0.1.3.dist-info/RECORD
